ConGUI/__init__.py
ConGUI_EroLIE-0.0.2.dist-info/LICENSE
ConGUI_EroLIE-0.0.2.dist-info/METADATA
ConGUI_EroLIE-0.0.2.dist-info/WHEEL
ConGUI_EroLIE-0.0.2.dist-info/top_level.txt
ConGUI_EroLIE-0.0.2.dist-info/RECORD
