Metadata-Version: 2.1
Name: ConGUI-EroLIE
Version: 0.0.2
Summary: ConGUI allows you to easily create console gui application without opening unicode table.
Home-page: https://github.com/pypa/sampleproject
Author: EroLIE
Author-email: michnoaz@gmail.com
License: UNKNOWN
Project-URL: Bug Tracker, https://github.com/pypa/sampleproject/issues
Platform: UNKNOWN
Classifier: Programming Language :: Python :: 3
Classifier: License :: OSI Approved :: MIT License
Classifier: Operating System :: OS Independent
Requires-Python: >=3.6
License-File: LICENSE
